jupyter_bokeh/__init__.py
jupyter_bokeh/_version.py
jupyter_bokeh/widgets.py
jupyter_bokeh/labextension/package.json
jupyter_bokeh/labextension/static/25.a1f00326924633b92ed3.js
jupyter_bokeh/labextension/static/7.2d4b977066efef2921dc.js
jupyter_bokeh/labextension/static/7.2d4b977066efef2921dc.js.LICENSE.txt
jupyter_bokeh/labextension/static/824.a3a1e45ab4137dbaadb5.js
jupyter_bokeh/labextension/static/remoteEntry.352adabd3ad00a55dce4.js
jupyter_bokeh/labextension/static/style.js
jupyter_bokeh/labextension/static/third-party-licenses.json
jupyter_bokeh/nbextension/extension.js
jupyter_bokeh/nbextension/index.js.LICENSE.txt
jupyter_bokeh-4.0.4.data/data/share/jupyter/labextensions/@bokeh/jupyter_bokeh/package.json
jupyter_bokeh-4.0.4.data/data/share/jupyter/labextensions/@bokeh/jupyter_bokeh/static/25.a1f00326924633b92ed3.js
jupyter_bokeh-4.0.4.data/data/share/jupyter/labextensions/@bokeh/jupyter_bokeh/static/7.2d4b977066efef2921dc.js
jupyter_bokeh-4.0.4.data/data/share/jupyter/labextensions/@bokeh/jupyter_bokeh/static/7.2d4b977066efef2921dc.js.LICENSE.txt
jupyter_bokeh-4.0.4.data/data/share/jupyter/labextensions/@bokeh/jupyter_bokeh/static/824.a3a1e45ab4137dbaadb5.js
jupyter_bokeh-4.0.4.data/data/share/jupyter/labextensions/@bokeh/jupyter_bokeh/static/remoteEntry.352adabd3ad00a55dce4.js
jupyter_bokeh-4.0.4.data/data/share/jupyter/labextensions/@bokeh/jupyter_bokeh/static/style.js
jupyter_bokeh-4.0.4.data/data/share/jupyter/labextensions/@bokeh/jupyter_bokeh/static/third-party-licenses.json
jupyter_bokeh-4.0.4.data/data/share/jupyter/labextensions/@bokeh/jupyter_bokeh/install.json
jupyter_bokeh-4.0.4.dist-info/METADATA
jupyter_bokeh-4.0.4.dist-info/WHEEL
jupyter_bokeh-4.0.4.dist-info/licenses/LICENSE.txt
jupyter_bokeh-4.0.4.dist-info/RECORD
