Metadata-Version: 2.1
Name: jupyter_bokeh
Version: 4.0.4
Summary: A Jupyter extension for rendering Bokeh content.
Project-URL: Homepage, https://github.com/bokeh/jupyter_bokeh
Project-URL: Bug Tracker, https://github.com/bokeh/jupyter_bokeh/issues
Project-URL: Repository, https://github.com/bokeh/jupyter_bokeh.git
Author-email: Bokeh team <info@bokeh.org>
License: Copyright (c) 2012 - 2020, Anaconda, Inc., and Bokeh Contributors
License-File: LICENSE.txt
Classifier: Development Status :: 5 - Production/Stable
Classifier: Framework :: Jupyter
Classifier: Framework :: Jupyter :: JupyterLab
Classifier: Framework :: Jupyter :: JupyterLab :: 4
Classifier: Framework :: Jupyter :: JupyterLab :: Extensions
Classifier: Framework :: Jupyter :: JupyterLab :: Extensions :: Prebuilt
Classifier: Intended Audience :: Developers
Classifier: Intended Audience :: Science/Research
Classifier: License :: OSI Approved :: BSD License
Classifier: Natural Language :: English
Classifier: Operating System :: OS Independent
Classifier: Programming Language :: Python
Classifier: Programming Language :: Python :: 3
Classifier: Programming Language :: Python :: 3.8
Classifier: Programming Language :: Python :: 3.9
Classifier: Programming Language :: Python :: 3.10
Classifier: Programming Language :: Python :: 3.11
Classifier: Topic :: Scientific/Engineering
Classifier: Topic :: Software Development :: Libraries
Requires-Python: >=3.8
Requires-Dist: bokeh==3.*
Requires-Dist: ipywidgets==8.*
Provides-Extra: all
Requires-Dist: jupyter-bokeh[build]; extra == 'all'
Requires-Dist: jupyter-bokeh[tests]; extra == 'all'
Provides-Extra: build
Requires-Dist: jupyterlab~=4.0; extra == 'build'
Requires-Dist: setuptools>=40.8.0; extra == 'build'
Provides-Extra: tests
Requires-Dist: flake8; extra == 'tests'
Requires-Dist: pytest; extra == 'tests'
